cdp_validator_for_aws/__init__.py
cdp_validator_for_aws/__main__.py
cdp_validator_for_aws/cdp_driver.py
cdp_validator_for_aws/networking.py
cdp_validator_for_aws/policy_manager.py
cdp_validator_for_aws/region.py
cdp_validator_for_aws/role.py
cdp_validator_for_aws/s3.py
cdp_validator_for_aws/security_groups.py
cdp_validator_for_aws/settings.py
cdp_validator_for_aws/policies/bucket-policy-s3access.json
cdp_validator_for_aws/policies/datalake-admin-policy-s3access.json
cdp_validator_for_aws/policies/dynamodb-policy.json
cdp_validator_for_aws/policies/ec2-role-trust-policy.json
cdp_validator_for_aws/policies/idbroker-assume-role-policy.json
cdp_validator_for_aws/policies/idbroker-role-trust-policy.json
cdp_validator_for_aws/policies/log-policy-s3access.json
cdp_validator_for_aws/policies/ranger-audit-policy-s3access.json
cdp_validator_for_aws-0.0.6.dist-info/LICENSE.txt
cdp_validator_for_aws-0.0.6.dist-info/LICENSE_SUPPLEMENTAL_DISCLAIMER.txt
cdp_validator_for_aws-0.0.6.dist-info/METADATA
cdp_validator_for_aws-0.0.6.dist-info/WHEEL
cdp_validator_for_aws-0.0.6.dist-info/top_level.txt
cdp_validator_for_aws-0.0.6.dist-info/RECORD
