Metadata-Version: 2.1
Name: cdp-validator-for-aws
Version: 0.0.6
Summary: Validation of aws resources used to create Cloudera Data Platform environments
Home-page: UNKNOWN
License: UNKNOWN
Platform: UNKNOWN
Classifier: Programming Language :: Python :: 3
Classifier: License :: OSI Approved :: Apache Software License
Classifier: Operating System :: OS Independent
Requires-Python: >=3.7
Requires-Dist: boto3 (>=1.9.242)
